{
  "문보경": {
    "등장곡": "ITZY - WANNABE",
    "응원가": "도시아이들 - 달빛 창가에서"
  },
  "최원영": {
    "등장곡": "2PM - Hands Up",
    "응원가": "구단 자작곡"
  },
  "신민재": {
    "등장곡": "Black Eyed Peas - Pump It",
    "응원가": "구단 자작곡"
  },
  "김주성": {
    "등장곡": "비트펠라 하우스 - Candy Thief",
    "응원가": "마야 - 위풍당당"
  },
  "구본혁": {
    "등장곡": "BIG Naughty - Vancouver 2",
    "응원가": "구단 자작곡"
  },
  "이영빈": {
    "등장곡": "G-DRAGON - 니가 뭔데",
    "응원가": "구단 자작곡"
  },
  "문성주": {
    "등장곡": "QWER - 고민중독",
    "응원가": "구단 자작곡"
  },
  "오지환": {
    "등장곡": "김바다 - Moonage Dream"
  },
  "김정율": {
    "등장곡": "Redbone - Come and Get Your Love",
    "응원가": "구단 자작곡"
  },
  "손용준": {
    "등장곡": "DAY6 - Zombie",
    "응원가": "은방울 자매 - 닐리리 맘보"
  },
  "박해민": {
    "등장곡": "블락비 - HER"
  },
  "오스틴 딘": {
    "등장곡": "TobyMac - I just need U.(Capital Kings Remix",
    "응원가": "구단 자작곡"
  },
  "함창건": {
    "등장곡": "Apink - LUV"
  },
  "박동원": {
    "응원가": "SG워너비 - 내 사랑 울보"
  },
  "추세현": {
    "등장곡": "Apink - Mr. Chu"
  },
  "김성진": {
    "등장곡": "The Phantoms - Made For This"
  },
  "홍창기": {
    "등장곡": "Panic! At The Disco - Victorious",
    "응원가": "홍경민 자작곡"
  },
  "이재원": {
    "등장곡": "JAXSON GAMBLE - Let's Go",
    "응원가": "구단 자작곡"
  },
  "천성호": {
    "등장곡": "비스트 - SHOCK",
    "응원가": "구단 자작곡"
  },
  "송찬의": {
    "등장곡": "i-dle - My Bag",
    "응원가": "구단 자작곡"
  },
  "문정빈": {
    "등장곡": "부석순 - 거침없이",
    "응원가": "쥬얼리 -"
  },
  "이주헌": {
    "등장곡": "카라 - Honey",
    "응원가": "구단 자작곡"
  },
  "박관우": {
    "등장곡": "SHINee - 링딩동",
    "응원가": "이은미 - 기억속으로"
  },
  "김현종": {
    "등장곡": "사이먼 도미닉 - 사이먼 도미닉"
  },
  "김범석": {
    "등장곡": "싸이 - 챔피언",
    "응원가": "구단 자작곡"
  },
  "김성우": {
    "등장곡": "강성 - 야인"
  },
  "김대원": {
    "등장곡": "Moon - No Matter How Hard We Try"
  },
  "김상현": {
    "응원가": "동요 - 모두 다 뛰놀자"
  },
  "김일경": {
    "응원가": "Bryan Adams - Summer of '69"
  },
  "김용의": {
    "등장곡": "BOBBY - 꽐라",
    "응원가": "영화"
  },
  "김재율": {
    "응원가": "Village People - Macho Man"
  },
  "강승호": {
    "등장곡": "Jim Yosef & Alex Skrindo - Passion",
    "응원가": "이승환 - 슈퍼 히어로"
  },
  "김민성": {
    "등장곡": "블락비 - 난리나",
    "응원가": "구단 자작곡"
  },
  "김재성": {
    "등장곡": "T-MAX - 파라다이스"
  },
  "김재현": {
    "응원가": "동요 - 모두 다 뛰놀자"
  },
  "김태군": {
    "등장곡": "딥플로우 - 작두",
    "응원가": "정삼 - 봤냐고"
  },
  "김태완": {
    "응원가": "동요 - '밀과 보리가 자라네"
  },
  "김호은": {
    "응원가": "구단자작곡"
  },
  "나성용": {
    "응원가": "박완규 - 욕망이라는 이름"
  },
  "라모스": {
    "등장곡": "비 - LA SONG",
    "응원가": "구단 자작곡"
  },
  "페타지니": {
    "응원가": "Dschinghis Khan - Dschinghis Khan"
  },
  "히메네스": {
    "등장곡": "Rebelution - Wake Up call",
    "응원가": "Dschinghis Khan - Dschinghis Khan"
  },
  "리오 루이즈": {
    "응원가": "구단 자작곡"
  },
  "로벨 가르시아": {
    "등장곡": "Bad Bunny - BENDICIONES",
    "응원가": "요하네스 브람스 - 헝가리 무곡 제5번"
  },
  "문선재": {
    "등장곡": "싸이 - 젠틀맨",
    "응원가": "체리필터 - 오리날다"
  },
  "박경수": {
    "응원가": "닐리리 맘보"
  },
  "박병호": {
    "응원가": "Village People - Macho Man"
  },
  "박용근": {
    "응원가": "이지연 - Love for Night"
  },
  "박용택": {
    "등장곡": "김범수 - 나타나",
    "응원가": "아리랑 목동"
  },
  "박재욱": {
    "응원가": "구단 자작곡"
  },
  "박지규": {
    "응원가": "동요 - 훌랄라 폴카"
  },
  "백창수": {
    "등장곡": "Flo Rida - Whistle",
    "응원가": "문차일드 - 태양은 가득히"
  },
  "스나이더": {
    "응원가": "Dschinghis Khan - Dschinghis Khan"
  },
  "서동욱": {
    "응원가": "노브레인 - Rock it Rocket"
  },
  "서상우": {
    "등장곡": "Moby - Extreme Ways",
    "응원가": "구단자작곡"
  },
  "서용빈": {
    "응원가": "369송"
  },
  "손인호": {
    "응원가": "닐리리 맘보"
  },
  "손주인": {
    "등장곡": "채환 - Fighting (파이팅)",
    "응원가": "닐리리 맘보"
  },
  "손지환": {
    "응원가": "윤형주 - 새우깡"
  },
  "심성보": {
    "응원가": "닐리리 맘보"
  },
  "아도니스 가르시아": {
    "응원가": "김준선 - 아라비안 나이트"
  },
  "안익훈": {
    "등장곡": "Alan Walker - The Drum",
    "응원가": "구단 자작곡"
  },
  "안재만": {
    "응원가": "클론 - 꿍따리 샤바라"
  },
  "안치용": {
    "응원가": "김아중 - 마리아"
  },
  "양석환": {
    "등장곡": "블락비 - Jackpot",
    "응원가": "Lady Gaga - Bad Romance"
  },
  "양영동": {
    "등장곡": "SHINee - 링딩동",
    "응원가": "Bill Haley - Rock Around the Clock"
  },
  "유지현": {
    "응원가": "닐리리 맘보"
  },
  "유강남": {
    "등장곡": "Hardwell & Tiesto - Colors,",
    "응원가": "Lady Gaga - The Edge of Glory"
  },
  "윤요섭": {
    "응원가": "Kelly Clarkson - My Life Would Suck Without You"
  },
  "윤진호": {
    "응원가": "ABBA - Waterloo"
  },
  "이대형": {
    "등장곡": "Black Eaed Peas - Pump It",
    "응원가": "Sato Naoki - Departure"
  },
  "이병규": {
    "등장곡": "W&W - Live The Night"
  },
  "이상호": {
    "응원가": "NC 구단 자작곡"
  },
  "이성우": {
    "응원가": "홍경민 자작곡"
  },
  "이종열": {
    "응원가": "동요 - 훌랄라 폴카"
  },
  "이주형": {
    "응원가": "영화"
  },
  "이형종": {
    "등장곡": "김민교 - 마지막 승부,",
    "응원가": "마야 - 위풍당당"
  },
  "알칸트라": {
    "응원가": "듣기"
  },
  "이진영": {
    "등장곡": "ASTER - Gucci Boy",
    "응원가": "트랜스 픽션 - 불의전차"
  },
  "이택근": {
    "응원가": "Kelly Clarkson - My Life Would Suck Without You"
  },
  "임훈": {
    "등장곡": "김태우 - 꿈을 꾸다",
    "응원가": "소녀의 기도"
  },
  "보어": {
    "응원가": "노브레인 - 미친듯 놀자"
  },
  "정근우": {
    "응원가": "홍경민 자작곡"
  },
  "정상호": {
    "등장곡": "LMNT - Juliet",
    "응원가": "원래 응원가가"
  },
  "정성훈": {
    "등장곡": "위대한 쇼맨",
    "응원가": "Hermann Necke -"
  },
  "정의윤": {
    "응원가": "김아중 - 마리아"
  },
  "한나한": {
    "응원가": "조용필 - 못찾겠다 꾀꼬리"
  },
  "조쉬 벨": {
    "등장곡": "다이나믹 듀오 - Ring My Bell",
    "응원가": "Bon Jovi - You Give Love A Bad Name"
  },
  "조윤준": {
    "등장곡": "레인보우 - Tell me Tell me",
    "응원가": "ABBA - Dancing Queen"
  },
  "조인성": {
    "등장곡": "MC 스나이퍼 - 민초의 난",
    "응원가": "ABBA - Dancing Queen"
  },
  "최경철": {
    "등장곡": "칠학년일반 - 오빠바이러스",
    "응원가": "토이"
  },
  "최동수": {
    "등장곡": "Linkin Park - 'What I've Done'",
    "응원가": "Queen - 'We will rock you'"
  },
  "최승준": {
    "응원가": "안치환-사람이 꽃보다 아름다워"
  },
  "최재원": {
    "등장곡": "방탄소년단 - 불타오르네",
    "응원가": "노브레인 - 미친듯 놀자"
  },
  "페게로": {
    "응원가": "구단자작곡"
  },
  "조셉": {
    "응원가": "Belinda Carlisle - Heaven Is A Place On Earth"
  },
  "현재윤": {
    "등장곡": "틴탑 - To you",
    "응원가": "Hanson - MMMbop"
  },
  "황목치승": {
    "응원가": "NRG - 할 수 있어"
  },
  "채은성": {
    "등장곡": "Carly Rae Jepsen - I Really Like You",
    "응원가": "트랜스픽션 - Devilman"
  },
  "서건창": {
    "응원가": "구단 자작곡"
  },
  "이천웅": {
    "응원가": "Kelly Clarkson - My Life Would Suck Without You"
  },
  "정주현": {
    "등장곡": "Maroon 5 - Lucky Strike",
    "응원가": "뉴질랜드 동요 - 예포이 타이타이"
  },
  "김기연": {
    "응원가": "구단 자작곡"
  },
  "손호영": {
    "응원가": "닐리리 맘보"
  },
  "최승민": {
    "등장곡": "DAY6 - 한 페이지가 될 수 있게",
    "응원가": "구단 자작곡"
  },
  "허도환": {
    "등장곡": "리쌍 - 광대",
    "응원가": "구단 자작곡(2023)"
  },
  "박정우": {
    "등장곡": "소녀시대 - 힘 내!",
    "응원가": "얀 - Run"
  },
  "박민": {
    "등장곡": "Serebro - Mi Mi Mi",
    "응원가": "이적 - 하늘을 달리다"
  },
  "김선빈": {
    "등장곡": "변진섭 - 새들처럼",
    "응원가": "바다새 - 바다새"
  },
  "김도영": {
    "등장곡": "All Time Low - Time-Bomb",
    "응원가": "럼블 피쉬 - Smile Again"
  },
  "이창진": {
    "등장곡": "Creepy Nuts - Bling-Bang-Bang-Born",
    "응원가": "WEPLAY - We"
  },
  "정현창": {
    "등장곡": "터치드 - Highlight",
    "응원가": "성시경 - 안녕 나의 사랑"
  },
  "김규성": {
    "등장곡": "가호 - Running",
    "응원가": "이승환 - 슈퍼히어로"
  },
  "박재현": {
    "응원가": "Miss Papaya - Hero"
  },
  "윤도현": {
    "등장곡": "IU - Shopper",
    "응원가": "FIELD OF VIEW - DAN DAN 心魅かれてく"
  },
  "주효상": {
    "등장곡": "Imagine Dragons - Warriors",
    "응원가": "SG워너비 - 해바라기"
  },
  "한준수": {
    "등장곡": "John Cena - The time is now"
  },
  "카스트로": {
    "등장곡": "趙雷 -",
    "응원가": "샤크라 - 난 너에게"
  },
  "김호령": {
    "등장곡": "이무진 - 청춘만화",
    "응원가": "강준우 - Go! Korea"
  },
  "변우혁": {
    "등장곡": "The Score - Stronger",
    "응원가": "Alan Walker - The Drum"
  },
  "데일": {
    "등장곡": "BewhY - Day Day",
    "응원가": "Dimitri Vegas & Like Mike - Beast"
  },
  "황대인": {
    "등장곡": "Sam Ryder - Tiny Riot",
    "응원가": "구단 자작곡"
  },
  "김석환": {
    "등장곡": "박재범 - All I Wanna Do (Feat. Hoody, Loco",
    "응원가": "자작곡"
  },
  "나성범": {
    "등장곡": "드렁큰 타이거 - Monster",
    "응원가": "이탈리아"
  },
  "양현종": {
    "등장곡": "Christina Aguilera - Fighter"
  },
  "오선우": {
    "등장곡": "Lil Nas X - STAR WALKIN'",
    "응원가": "TUBE - The Season In The Sun"
  },
  "고종욱": {
    "등장곡": "Galantis - Rich Boy"
  },
  "이범호": {
    "등장곡": "리쌍 - Yes, Ok (Feat."
  },
  "이종범": {
    "등장곡": "YG FAMILY - 멋쟁이 신사",
    "응원가": "펩시맨"
  },
  "강경학": {
    "응원가": "크레용팝 - 어이"
  },
  "김다원": {
    "등장곡": "김영철 - 힘을 내요 슈퍼파워",
    "응원가": "Jedward - Give It Up"
  },
  "김민우": {
    "등장곡": "배치기 - No.3 (Feat. Sol Flower"
  },
  "김상훈": {
    "등장곡": "해바라기 - 그대 내게 행복을 주는 사람"
  },
  "김원섭": {
    "등장곡": "Patty Ryan - You're My Love('98 Extended Ver.)"
  },
  "김종국": {
    "응원가": "함중아 - 내게도 사랑이"
  },
  "김주찬": {
    "등장곡": "Five - Everybody Get Up",
    "응원가": "Mary Hopkins -"
  },
  "김주형": {
    "등장곡": "본 조비 - It's My Life",
    "응원가": "노브레인 - 그것이 젊음"
  },
  "나주환": {
    "응원가": "DJ DOC - DOC와 춤을..."
  },
  "류승현": {
    "응원가": "케냐"
  },
  "류은재": {
    "응원가": "Craig David - Insomnia"
  },
  "박경태": {
    "응원가": "Cliff Richard - Early in the Morning"
  },
  "박준태": {
    "등장곡": "스크릴렉스 - Bangarang"
  },
  "서재응": {
    "응원가": "Ray Charles - I Can't Stop Loving You"
  },
  "송산": {
    "응원가": "The Crack -"
  },
  "오준혁": {
    "등장곡": "스컬 - Ragga Muffin",
    "응원가": "센치한 - 찹쌀떡"
  },
  "유민상": {
    "응원가": "Elvis Presley - Love Me Tender"
  },
  "윤석민": {
    "응원가": "싸이 - 아버지"
  },
  "윤해진": {
    "등장곡": "Pitbull - Feel This Moment (Feat. Christina Aguilera"
  },
  "이명기": {
    "등장곡": "하이라이트 - 얼굴 찌푸리지 말아요",
    "응원가": "노브레인 - 별이 되어"
  },
  "이재주": {
    "응원가": "김추자 - 무인도"
  },
  "이준호": {
    "응원가": "플라워 - 축제"
  },
  "이홍구": {
    "등장곡": "Mark Ronson - Uptown Funk!",
    "응원가": "베토벤 - 엘리제를 위하여"
  },
  "임준섭": {
    "응원가": "The Beatles - Hey Jude"
  },
  "장성호": {
    "등장곡": "장윤정 - 사랑아",
    "응원가": "Johnny I Hardly Knew Ye"
  },
  "장영석": {
    "응원가": "이탈리아"
  },
  "조영훈": {
    "응원가": "조용필 - 청춘시대"
  },
  "채종범": {
    "응원가": "홈플러스"
  },
  "최용규": {
    "등장곡": "Maroon 5 - Lucky Strike",
    "응원가": "Yoshimata Ryo - 1997 Spring"
  },
  "최희섭": {
    "등장곡": "Jean Roch - Can You Feel It"
  },
  "한기주": {
    "응원가": "김추자 - 무인도"
  },
  "홍세완": {
    "응원가": "현숙 - 정말로"
  },
  "황윤호": {
    "응원가": "세르게이 라흐마니노프 - 교향곡 2번 제3악장"
  },
  "황정립": {
    "응원가": "Stevie Wonder - Part-Time Lover"
  },
  "강한울": {
    "등장곡": "Les Trashick - Polish Up My Trumpet",
    "응원가": "The Crack - 코리아 오 코리아"
  },
  "김민식": {
    "응원가": "홀라당 - 밀어붙여"
  },
  "김태진": {
    "응원가": "NC 다이노스"
  },
  "노수광": {
    "응원가": "싸이 - 오늘 밤새"
  },
  "류지혁": {
    "등장곡": "EXO - Love Shot"
  },
  "송은범": {
    "응원가": "싸이 - Never Say Goodbye"
  },
  "신범수": {
    "등장곡": "Bishop Briggs - Revolution",
    "응원가": "Dimitri Vegas & Like Mike - Ocarina (Feat. Wolfpack)"
  },
  "안치홍": {
    "등장곡": "방탄소년단 - IDOL"
  },
  "이용규": {
    "등장곡": "박현빈 - 샤방샤방"
  },
  "이우성": {
    "등장곡": "이홍기 - 말이야",
    "응원가": "Alan Walker"
  },
  "이정훈": {
    "등장곡": "세븐틴 - 박수"
  },
  "최원준": {
    "등장곡": "도겸 - GO!",
    "응원가": "Every Single Day - Super Power Girl"
  },
  "한승혁": {
    "응원가": "김창선 -"
  },
  "홍종표": {
    "등장곡": "형용돈죵 - 해볼라고",
    "응원가": "M4 - 널 위한 멜로디"
  },
  "박찬호": {
    "응원가": "M4 - 널 위한 멜로디"
  },
  "최형우": {
    "등장곡": "장기하와 얼굴들 - 풍문으로 들었소"
  },
  "버나디나": {
    "등장곡": "Bellini -",
    "응원가": "Stephen Foster - Camptown Races"
  },
  "터커": {
    "등장곡": "Criminal Vibes - Mambo No.5 (Club Remix)",
    "응원가": "강남 - 댁이나 잘하세요"
  },
  "필": {
    "등장곡": "Pharrell Williams - Happy",
    "응원가": "McFly - All About You"
  },
  "해즐베이커": {
    "응원가": "구단 자작곡"
  },
  "소크라테스": {
    "등장곡": "Blasterjaxx - Narco",
    "응원가": "Blasterjaxx - Narco"
  },
  "위즈덤": {
    "응원가": "Harold Faltermeyer,"
  },
  "선동열": {
    "응원가": "Jimmy Davis"
  },
  "고승민": {
    "등장곡": "The Script & will.i.am - Hall Of Fame"
  },
  "한태양": {
    "등장곡": "마이클 부블레 - Feeling Good"
  },
  "최항": {
    "등장곡": "원필 - 행운을 빌어 줘"
  },
  "신윤후": {
    "등장곡": "시크릿 - Yoo Hoo"
  },
  "조세진": {
    "등장곡": "Flo Rida - Whistle"
  },
  "장두성": {
    "등장곡": "Fall Out Of Boy - The Last Of The Real Ones"
  },
  "빅터 레이예스": {
    "등장곡": "TWICE - Yes or Yes"
  },
  "김동혁": {
    "등장곡": "Kelly Clarkson - Stronger"
  },
  "윤동희": {
    "등장곡": "Bishop Briggs - CHAMPION"
  },
  "김성배": {
    "등장곡": "Moby - Extreme Ways"
  },
  "손승락": {
    "등장곡": "나다 - King pin(Feat."
  },
  "송승준": {
    "등장곡": "The Phoenix - Fall out boy"
  },
  "강민호": {
    "등장곡": "노브레인 - 넌 내게 반했어"
  },
  "나원탁": {
    "등장곡": "철싸("
  },
  "용덕한": {
    "등장곡": "Bon Jovi - It's My Life"
  },
  "장성우": {
    "등장곡": "DJ Khaled - All I Do Is Win"
  },
  "김대륙": {
    "등장곡": "Cherry Filter - 낭만고양이"
  },
  "김대우": {
    "등장곡": "Roy Jones - Can`t be touched"
  },
  "김동한": {
    "등장곡": "Martin Garrix"
  },
  "김민수": {
    "등장곡": "Graham Blvd - Come and Get Your Love (From \"Avengers:Endgame\")"
  },
  "김상호": {
    "등장곡": "GD X TAEYANG - GOOD BOY"
  },
  "문규현": {
    "등장곡": "Tungevaag, Raaban -"
  },
  "박기혁": {
    "등장곡": "Henry Fong - Stand Up (Original Mix)"
  },
  "박종윤": {
    "등장곡": "장미 - 꿀이다"
  },
  "박준서": {
    "등장곡": "대성 - 날개"
  },
  "신본기": {
    "등장곡": "슈프림팀 - 땡땡땡"
  },
  "앤디 번즈": {
    "등장곡": "Showtek - Booyah (Original Mix)"
  },
  "오태곤": {
    "등장곡": "DJ HANMIN - Show Me Your BBA SAE (Feat. Ingram Jones)"
  },
  "이대호": {
    "등장곡": "Harry Belafonte - Day-O"
  },
  "이호연": {
    "등장곡": "Post Malone - Motley Clew"
  },
  "정훈": {
    "등장곡": "Bingo Player - Get Up"
  },
  "조성환": {
    "등장곡": "이적 - 하늘을 달리다"
  },
  "채태인": {
    "등장곡": "Jessy Matador - Bomba"
  },
  "최준석": {
    "등장곡": "LMFAO - Shots"
  },
  "카를로스 아수아헤": {
    "등장곡": "존니 - 살아있네 (Feat."
  },
  "황재균": {
    "등장곡": "스페이스 에이 - 섹시한 남자"
  },
  "황진수": {
    "등장곡": "박상철 - 황진이"
  },
  "김문호": {
    "등장곡": "Ylvis - The Fox"
  },
  "김민하": {
    "등장곡": "Henry Fong - Stand Up (Original Mix)"
  },
  "김주현": {
    "등장곡": "블락비 - HER"
  },
  "나경민": {
    "등장곡": "허각 - 하늘을 달리다"
  },
  "민병헌": {
    "등장곡": "BIGBANG - 뱅뱅뱅"
  },
  "손아섭": {
    "등장곡": "장미여관 - 오빠라고 불러다오"
  },
  "안권수": {
    "등장곡": "Fly Project -"
  },
  "잭 렉스": {
    "등장곡": "Good Charlotte - Lifestyles of the Rich & Famous"
  },
  "짐 아두치": {
    "등장곡": "John Cena - The time is now"
  },
  "추재현": {
    "등장곡": "NCT DREAM - Chewing Gum"
  },
  "디아즈": {
    "등장곡": "지코 - Artist"
  },
  "이해승": {
    "등장곡": "Alan Walker - The Drum"
  },
  "심재훈": {
    "등장곡": "다이나믹 듀오,이영지 - Smoke"
  },
  "이재현": {
    "등장곡": "Blackpink - Kill This Love"
  },
  "김재혁": {
    "등장곡": "BIGBANG(빅뱅) - 붉은 노을"
  },
  "이성규": {
    "등장곡": "Jagwar Twin - Happy Face"
  },
  "김재상": {
    "등장곡": "구단 자작곡"
  },
  "이병헌": {
    "등장곡": "Kodak Black - ZEZE(Feat.Travis Scott & Offset)"
  },
  "김도환": {
    "등장곡": "구단 자작곡"
  },
  "김태훈": {
    "등장곡": "아스터(ASTER) - Gucci"
  },
  "김영웅": {
    "등장곡": "MC몽 - 인기"
  },
  "윤정빈": {
    "등장곡": "RIIZE - Siren"
  },
  "김헌곤": {
    "등장곡": "DAY6(데이식스) - 한 페이지가 될 수 있게"
  },
  "김성윤": {
    "등장곡": "Eric Clapton - Layla"
  },
  "함수호": {
    "등장곡": "G-DRAGON - 크레용"
  },
  "류승민": {
    "등장곡": "Epiik, BEOM (KOR), Arkins - Bongduck Rangers"
  },
  "이창용": {
    "등장곡": "블락비 - Nalina"
  },
  "박세혁": {
    "등장곡": "DJ Hanmin - Show Me Your BBA SAE"
  },
  "양우현": {
    "등장곡": "Various Artist - 굿데이 2025"
  },
  "김지찬": {
    "등장곡": "Gummibar - Gummy Bear Song"
  },
  "전병우": {
    "등장곡": "슈프림팀 - 땡땡땡"
  },
  "박승규": {
    "등장곡": "Black GrpyhOn & Baasik - Insane"
  },
  "조민성": {
    "등장곡": "Bishop Briggs - White Flag"
  },
  "김현준": {
    "등장곡": "DEAN - 21"
  },
  "이도윤": {
    "등장곡": "세븐틴 - 손오공",
    "응원가": "타카피 - Let it Rain"
  },
  "심우준": {
    "등장곡": "5 Seconds of Summer - Teeth",
    "응원가": "페퍼톤스 - Superfantastic"
  },
  "노시환": {
    "등장곡": "터보트로닉 - say yes",
    "응원가": "트랜스픽션 - Mary Jane"
  },
  "최재훈": {
    "등장곡": "싸이(PSY) - 예술이야",
    "응원가": "박일송 - 케세라세라"
  },
  "하주석": {
    "등장곡": "주석 - 정상을 향한 독주 2",
    "응원가": "구단 자작곡"
  },
  "권광민": {
    "등장곡": "G-DRAGON (지드래곤) - HOME SWEET HOME"
  },
  "김태연": {
    "등장곡": "Timbaland - The Way I Are",
    "응원가": "디지몬 어드벤처 OST"
  },
  "페라자": {
    "등장곡": "LE SSERAFIM - ANTIFRAGILE",
    "응원가": "징키스탄"
  },
  "유로결": {
    "등장곡": "엔플라잉 - Blue Moon"
  },
  "이원석": {
    "등장곡": "BE'O (비오) - LOVE me",
    "응원가": "벅 - 맨발의 청춘"
  },
  "최인호": {
    "등장곡": "Cash Cash - Overtime",
    "응원가": "Sun Stroke Project & Oila Tira - Run Away"
  },
  "박상언": {
    "등장곡": "One Direction - What Makes You Beautiful",
    "응원가": "이현섭 - 내 인생의 스페셜"
  },
  "강백호": {
    "등장곡": "모네스킨 - Beggin'",
    "응원가": "토이 - 뜨거운 안녕"
  },
  "문현빈": {
    "등장곡": "울랄라세션 - 미인",
    "응원가": "타이푼 - 사랑을 주세요"
  },
  "허인서": {
    "등장곡": "지코 - 괴짜",
    "응원가": "트랜스픽션 - Get Show"
  },
  "박정현": {
    "등장곡": "STAYC - POPPY",
    "응원가": "다비치 - 안녕이라고 말하지마"
  },
  "황영묵": {
    "등장곡": "OTHANKQ - 블랙팬서 (Black Panther)",
    "응원가": "트랜스픽션 - 너를 원해"
  },
  "류현진": {
    "등장곡": "제드 - 코리안 몬스터",
    "응원가": "블레이디 - 미친날"
  },
  "정은원": {
    "등장곡": "마이티 마우스 - 에너지"
  }
}